dtweb/__init__.py
dtweb/client.py
dtweb-0.0.1.dist-info/LICENSE
dtweb-0.0.1.dist-info/METADATA
dtweb-0.0.1.dist-info/WHEEL
dtweb-0.0.1.dist-info/top_level.txt
dtweb-0.0.1.dist-info/RECORD
