Metadata-Version: 2.1
Name: dtweb
Version: 0.0.1
Summary: Python library for accessing the Digital Twin Web
Home-page: https://github.com/juusoautiosalo/dtweb-python
Author: Juuso Autiosalo
Author-email: juuso.autiosalo@iki.fi
License: MIT
Platform: UNKNOWN
Classifier: Programming Language :: Python :: 3
Classifier: License :: OSI Approved :: MIT License
Classifier: Operating System :: OS Independent
Requires-Python: >=3.8
Requires-Dist: requests
